ljobx/__init__.py
ljobx/api/__init__.py
ljobx/api/linkedin_client.py
ljobx/api/proxy/__init__.py
ljobx/api/proxy/file_proxy_provider.py
ljobx/api/proxy/proxy_manager.py
ljobx/api/proxy/proxy_provider.py
ljobx/api/proxy/webshare_provider.py
ljobx/core/__init__.py
ljobx/core/cli.py
ljobx/core/config.py
ljobx/core/config_loader.py
ljobx/core/scraper.py
ljobx/ui/__init__.py
ljobx/ui/main.py
ljobx/ui/web_ui.py
ljobx/ui/.streamlit/config.toml
ljobx/ui/.streamlit/icon.png
ljobx/utils/__init__.py
ljobx/utils/const.py
ljobx/utils/logger.py
ljobx-2.2.0.dist-info/METADATA
ljobx-2.2.0.dist-info/WHEEL
ljobx-2.2.0.dist-info/entry_points.txt
ljobx-2.2.0.dist-info/top_level.txt
ljobx-2.2.0.dist-info/RECORD
