Metadata-Version: 2.4
Name: ljobx
Version: 2.2.0
Summary: A powerful, asynchronous scraper for LinkedIn job postings without authentication.
Author-email: Tushar Kumar <tusharkr1918@gmail.com>
License-Expression: MIT
Project-URL: Homepage, https://github.com/tusharkr1918/ljobx
Classifier: Programming Language :: Python :: 3
Classifier: Programming Language :: Python :: 3.10
Classifier: Programming Language :: Python :: 3.11
Classifier: Programming Language :: Python :: 3.12
Classifier: Operating System :: OS Independent
Classifier: Topic :: Internet :: WWW/HTTP :: Indexing/Search
Requires-Python: >=3.10
Requires-Dist: httpx[socks]>=0.27.0
Requires-Dist: beautifulsoup4>=4.13.5
Requires-Dist: fake-useragent>=2.2.0
Requires-Dist: PyYAML~=6.0.2
Provides-Extra: ui
Requires-Dist: pandas~=2.3.2; extra == "ui"
Requires-Dist: streamlit~=1.50.0; extra == "ui"
Requires-Dist: streamlit-local-storage~=0.0.25; extra == "ui"
